helmi/__init__.py
helmi/forms.py
helmi/helmholtz.py
helmi/helper.py
Helmi_FEM-0.3.0.dist-info/LICENSE
Helmi_FEM-0.3.0.dist-info/METADATA
Helmi_FEM-0.3.0.dist-info/WHEEL
Helmi_FEM-0.3.0.dist-info/top_level.txt
Helmi_FEM-0.3.0.dist-info/RECORD
