Metadata-Version: 2.1
Name: Helmi-FEM
Version: 0.3.0
Summary: Finite element method for solving the electromagnetic Helmholtz equation.
Author: Vincent R.
Maintainer: Vincent R.
License: BSD 3-Clause License
Project-URL: homepage, https://github.com/Vinc0110/Helmi_FEM
Project-URL: repository, https://github.com/Vinc0110/Helmi_FEM.git
Keywords: Helmholtz equation,finite-element analysis,finite-element method
Classifier: Development Status :: 4 - Beta
Classifier: Programming Language :: Python :: 3
Classifier: Intended Audience :: Science/Research
Classifier: License :: OSI Approved :: BSD License
Classifier: Operating System :: OS Independent
Requires-Python: >=3.8
License-File: LICENSE
Requires-Dist: scikit-fem
Requires-Dist: meshio
Requires-Dist: numpy
Requires-Dist: scipy
Provides-Extra: mesh
Requires-Dist: gmsh ; extra == 'mesh'
Provides-Extra: plot
Requires-Dist: matplotlib ; extra == 'plot'
